LICENSE
MANIFEST.in
README.rst
requirements.txt
setup.py
django_experiments.egg-info/PKG-INFO
django_experiments.egg-info/SOURCES.txt
django_experiments.egg-info/dependency_links.txt
django_experiments.egg-info/requires.txt
django_experiments.egg-info/top_level.txt
experiments/__init__.py
experiments/admin.py
experiments/admin_utils.py
experiments/apps.py
experiments/conf.py
experiments/counters.py
experiments/dateutils.py
experiments/experiment_counters.py
experiments/manager.py
experiments/middleware.py
experiments/models.py
experiments/signal_handlers.py
experiments/signals.py
experiments/significance.py
experiments/stats.py
experiments/urls.py
experiments/utils.py
experiments/views.py
experiments/migrations/0001_initial.py
experiments/migrations/__init__.py
experiments/south_migrations/0001_initial.py
experiments/south_migrations/0002_auto__chg_field_enrollment_goals_.py
experiments/south_migrations/0003_auto__del_field_enrollment_goals__add_field_enrollment_last_seen__chg_.py
experiments/south_migrations/__init__.py
experiments/static/experiments/dashboard/css/admin.css
experiments/static/experiments/dashboard/js/admin.js
experiments/static/experiments/dashboard/js/csrf.js
experiments/static/experiments/js/experiments.js
experiments/static/experiments/js/jquery.cookie.js
experiments/templates/admin/experiments/change_form.html
experiments/templates/admin/experiments/results_table.html
experiments/templates/experiments/confirm_human.html
experiments/templates/experiments/goal.html
experiments/templatetags/__init__.py
experiments/templatetags/experiments.py
experiments/tests/__init__.py
experiments/tests/test_admin.py
experiments/tests/test_counter.py
experiments/tests/test_signals.py
experiments/tests/test_significance.py
experiments/tests/test_templatetags.py
experiments/tests/test_webuser.py
experiments/tests/test_webuser_incorporate.py
experiments/tests/urls.py