Metadata-Version: 1.0
Name: django-experiments
Version: 1.1.5
Summary: Python Django AB Testing Framework
Home-page: https://github.com/mixcloud/django-experiments
Author: Mixcloud
Author-email: technical@mixcloud.com
License: MIT license, see LICENSE file
Platform: UNKNOWN
